SpotSegmentation/__init__.py
SpotSegmentation/.weights/unet_resnet_naturalSpots_dataset_notscaled
SpotSegmentation/src/SpotSegmenter.py
SpotSegmentation/src/__init__.py
SpotSegmentation/src/utils.py
SpotSegmentation-0.5.dist-info/LICENSE
SpotSegmentation-0.5.dist-info/METADATA
SpotSegmentation-0.5.dist-info/WHEEL
SpotSegmentation-0.5.dist-info/top_level.txt
SpotSegmentation-0.5.dist-info/RECORD
